PyNvVideoCodec/PyNvVideoCodec_121.cp310-win_amd64.pyd
PyNvVideoCodec/PyNvVideoCodec_130.cp310-win_amd64.pyd
PyNvVideoCodec/VersionCheck.cp310-win_amd64.pyd
PyNvVideoCodec/__init__.py
PyNvVideoCodec/avcodec-58.dll
PyNvVideoCodec/avcodec-61.dll
PyNvVideoCodec/avcodec.dll
PyNvVideoCodec/avdevice-58.dll
PyNvVideoCodec/avdevice-61.dll
PyNvVideoCodec/avdevice.dll
PyNvVideoCodec/avfilter-10.dll
PyNvVideoCodec/avfilter-7.dll
PyNvVideoCodec/avfilter.dll
PyNvVideoCodec/avformat-58.dll
PyNvVideoCodec/avformat-61.dll
PyNvVideoCodec/avformat.dll
PyNvVideoCodec/avutil-56.dll
PyNvVideoCodec/avutil-59.dll
PyNvVideoCodec/avutil.dll
PyNvVideoCodec/swresample-3.dll
PyNvVideoCodec/swresample-5.dll
PyNvVideoCodec/swresample.dll
PyNvVideoCodec/swscale-5.dll
PyNvVideoCodec/swscale-8.dll
PyNvVideoCodec/swscale.dll
PyNvVideoCodec/decoders/SimpleDecoder.py
PyNvVideoCodec/decoders/ThreadedDecoder.py
PyNvVideoCodec/decoders/__init__.py
PyNvVideoCodec/transcoder/Transcoder.py
PyNvVideoCodec/transcoder/__init__.py
benchmarks/cached_decoder_benchmark.py
benchmarks/frame_sampling_benchmark.py
benchmarks/requirements.txt
benchmarks/segmented_transcode_benchmark.py
pynvvideocodec-2.1.0.data/data/external/ffmpeg/readme.txt
pynvvideocodec-2.1.0.data/data/external/ffmpeg/src/ffmpeg-7.0.2.tar.xz
pynvvideocodec-2.1.0.dist-info/licenses/LICENSE.txt
pynvvideocodec-2.1.0.dist-info/licenses/NOTICES.txt
samples/requirements.txt
samples/advanced/decode.py
samples/advanced/decode_from_memory_buffer.py
samples/advanced/decode_perf.py
samples/advanced/decode_reconfigure.py
samples/advanced/decode_sei_msg.py
samples/advanced/decode_with_cuda_control.py
samples/advanced/decode_with_low_latency.py
samples/advanced/encode_config.json
samples/advanced/encode_config_lowlatency.json
samples/advanced/encode_perf.py
samples/advanced/encode_reconfigure.py
samples/advanced/encode_sei_msg.py
samples/advanced/simple_decode_stats.py
samples/basic/create_video_segments.py
samples/basic/encode.py
samples/basic/encode_config.json
samples/basic/segments.txt
samples/basic/simple_decode_sampling.py
samples/basic/transcode_config.json
pynvvideocodec-2.1.0.dist-info/METADATA
pynvvideocodec-2.1.0.dist-info/WHEEL
pynvvideocodec-2.1.0.dist-info/top_level.txt
pynvvideocodec-2.1.0.dist-info/RECORD
