Metadata-Version: 2.4
Name: pynvvideocodec
Version: 2.1.0
Summary: pynvvideocodec (PyNvVideoCodec) is NVIDIA's Python library for hardware-accelerated video encode/decode on NVIDIA GPUs.
Author: NVIDIA
Maintainer: nvidia
License: MIT
Project-URL: documentation, https://docs.nvidia.com/video-technologies/pynvvideocodec/index.html
Project-URL: source, https://catalog.ngc.nvidia.com/orgs/nvidia/resources/pynvvideocodec
Classifier: License :: OSI Approved :: MIT License
Requires-Python: >=3.8
License-File: LICENSE.txt
License-File: NOTICES.txt
Dynamic: license-file
